gorkhadev/__init__.py
gorkhadev/info.py
gorkhadev-0.0.1.dist-info/LICENSE
gorkhadev-0.0.1.dist-info/METADATA
gorkhadev-0.0.1.dist-info/WHEEL
gorkhadev-0.0.1.dist-info/top_level.txt
gorkhadev-0.0.1.dist-info/RECORD
